gpix/__init__.py
gpix/pyx.py
gpix/pyxelate.py
gpix-0.1.0.dist-info/entry_points.txt
gpix-0.1.0.dist-info/WHEEL
gpix-0.1.0.dist-info/METADATA
gpix-0.1.0.dist-info/RECORD
