Metadata-Version: 2.1
Name: gpix
Version: 0.1.0
Summary: 
Author: guojian
Requires-Python: >=3.9,<4.0
Classifier: Programming Language :: Python :: 3
Classifier: Programming Language :: Python :: 3.9
Requires-Dist: pillow (>=8.0.1,<9.0.0)
Requires-Dist: pytest (>=6.1.2,<7.0.0)
Requires-Dist: pywavelets (>=1.1.1,<2.0.0)
Requires-Dist: scikit-image (>=0.17.2,<0.18.0)
Requires-Dist: scikit-learn (>=0.23.2,<0.24.0)
Requires-Dist: tifffile (>=2020.11.18,<2021.0.0)
